tf_complex/__init__.py
tf_complex/activations.py
tf_complex/convolutions.py
tf_complex/dense.py
tf_complex-0.0.3.dist-info/LICENSE
tf_complex-0.0.3.dist-info/METADATA
tf_complex-0.0.3.dist-info/WHEEL
tf_complex-0.0.3.dist-info/top_level.txt
tf_complex-0.0.3.dist-info/RECORD
